repro2/__init__.py
repro2/__main__.py
repro2/testing.py
repro2/commands/__init__.py
repro2/commands/predict.py
repro2/commands/pull.py
repro2/commands/setup.py
repro2/commands/subcommand.py
repro2/commands/util.py
repro2/commands/version.py
repro2/common/__init__.py
repro2/common/checks.py
repro2/common/docker.py
repro2/common/io.py
repro2/common/logging.py
repro2/common/registrable.py
repro2/common/tempdir.py
repro2/common/util.py
repro2/data/__init__.py
repro2/data/types.py
repro2/data/dataset_readers/__init__.py
repro2/data/dataset_readers/dataset_reader.py
repro2/data/dataset_readers/datasets.py
repro2/data/dataset_readers/jsonl.py
repro2/data/dataset_readers/sacrerouge.py
repro2/data/output_writers/__init__.py
repro2/data/output_writers/default.py
repro2/data/output_writers/metrics.py
repro2/data/output_writers/output_writer.py
repro2/data/output_writers/sacrerouge.py
repro2/models/__init__.py
repro2/models/model.py
repro2/models/chen2020/__init__.py
repro2/models/chen2020/dataset_reader.py
repro2/models/chen2020/models.py
repro2/models/chen2020/setup.py
repro2/models/colombo2021/__init__.py
repro2/models/colombo2021/models.py
repro2/models/colombo2021/setup.py
repro2/models/denkowski2014/__init__.py
repro2/models/denkowski2014/model.py
repro2/models/denkowski2014/setup.py
repro2/models/deutsch2021/__init__.py
repro2/models/deutsch2021/dataset_reader.py
repro2/models/deutsch2021/models.py
repro2/models/deutsch2021/setup.py
repro2/models/dou2021/__init__.py
repro2/models/dou2021/commands.py
repro2/models/dou2021/dataset_reader.py
repro2/models/dou2021/models.py
repro2/models/dou2021/setup.py
repro2/models/dugan2020/__init__.py
repro2/models/dugan2020/model.py
repro2/models/dugan2020/setup.py
repro2/models/durmus2020/__init__.py
repro2/models/durmus2020/model.py
repro2/models/durmus2020/setup.py
repro2/models/fitzgerald2018/__init__.py
repro2/models/fitzgerald2018/model.py
repro2/models/fitzgerald2018/setup.py
repro2/models/gao2020/__init__.py
repro2-0.0.5.dist-info/METADATA
repro2-0.0.5.dist-info/WHEEL
repro2-0.0.5.dist-info/RECORD
