Metadata-Version: 2.4
Name: repro2
Version: 0.0.5
Summary: An open-source library for reproducing results from research papers
Requires-Python: >=3.12
Requires-Dist: datasets>=3.4.1
Requires-Dist: docker>=7.1.0
Requires-Dist: joblib>=1.4.2
Requires-Dist: lark>=1.2.2
Requires-Dist: overrides>=7.7.0
Requires-Dist: pytest>=8.3.5
Requires-Dist: six>=1.17.0
